simple_io_kit-1.0.0.dist-info/licenses/LICENSE
simpleio/__init__.py
simpleio/simpleio.py
simple_io_kit-1.0.0.dist-info/METADATA
simple_io_kit-1.0.0.dist-info/WHEEL
simple_io_kit-1.0.0.dist-info/top_level.txt
simple_io_kit-1.0.0.dist-info/RECORD
