Metadata-Version: 2.4
Name: simple-io-kit
Version: 1.0.0
Summary: Simple and easy-to-use file and JSON I/O utilities.
Author-email: Raed Mughaus <you@example.com>
License:                                  Apache License
Project-URL: Homepage, https://github.com/yourusername/simplerio
Requires-Python: >=3.7
License-File: LICENSE
Dynamic: license-file
